purl_license_checker/__init__.py
purl_license_checker/cli.py
purl_license_checker/parser.py
purl_license_checker-0.3.0.dist-info/WHEEL
purl_license_checker-0.3.0.dist-info/entry_points.txt
purl_license_checker-0.3.0.dist-info/METADATA
purl_license_checker-0.3.0.dist-info/RECORD
